odoo/addons/base_old_migration_fields/README.rst
odoo/addons/base_old_migration_fields/__init__.py
odoo/addons/base_old_migration_fields/__manifest__.py
odoo/addons/base_old_migration_fields/i18n/es.po
odoo/addons/base_old_migration_fields/readme/CONTRIBUTORS.md
odoo/addons/base_old_migration_fields/readme/DESCRIPTION.md
odoo/addons/base_old_migration_fields/readme/USAGE.md
odoo/addons/base_old_migration_fields/security/base_old_migration_fields_security.xml
odoo/addons/base_old_migration_fields/static/description/icon.png
odoo/addons/base_old_migration_fields/static/description/index.html
odoo_addon_base_old_migration_fields-18.0.1.0.0.1.dist-info/METADATA
odoo_addon_base_old_migration_fields-18.0.1.0.0.1.dist-info/WHEEL
odoo_addon_base_old_migration_fields-18.0.1.0.0.1.dist-info/top_level.txt
odoo_addon_base_old_migration_fields-18.0.1.0.0.1.dist-info/RECORD
